hadoopinspector
prod
