Metadata-Version: 1.1
Name: hadoop-inspector
Version: 0.1.6
Summary: A measurement and inspection tool to manage Hadoop data quality, manageability and health
Home-page: http://github.com/willzfarmer/HadoopInspector
Author: Will Farmer, Ken Farmer
Author-email: willzfarmer@gmail.com, kenfar@gmail.com
License: BSD
Keywords: data quality management health
Platform: UNKNOWN
Classifier: Development Status :: 4 - Beta
Classifier: Environment :: Console
Classifier: Intended Audience :: Information Technology
Classifier: Intended Audience :: Science/Research
Classifier: License :: OSI Approved :: BSD License
Classifier: Programming Language :: Python :: 2
Classifier: Operating System :: POSIX
Classifier: Topic :: Database
Classifier: Topic :: Scientific/Engineering :: Information Analysis
